langchain_google_genai/__init__.py
langchain_google_genai/_common.py
langchain_google_genai/_enums.py
langchain_google_genai/_function_utils.py
langchain_google_genai/_genai_extension.py
langchain_google_genai/_image_utils.py
langchain_google_genai/chat_models.py
langchain_google_genai/embeddings.py
langchain_google_genai/genai_aqa.py
langchain_google_genai/google_vector_store.py
langchain_google_genai/llms.py
langchain_google_genai/py.typed
gigachain_google_genai-2.0.0.dist-info/LICENSE
gigachain_google_genai-2.0.0.dist-info/METADATA
gigachain_google_genai-2.0.0.dist-info/WHEEL
gigachain_google_genai-2.0.0.dist-info/RECORD
