Metadata-Version: 2.1
Name: gigachain-google-genai
Version: 2.0.0
Summary: An integration package connecting Google's genai package and GigaChain
Home-page: https://github.com/langchain-ai/langchain-google
License: MIT
Requires-Python: >=3.9,<4.0
Classifier: License :: OSI Approved :: MIT License
Classifier: Programming Language :: Python :: 3
Classifier: Programming Language :: Python :: 3.9
Classifier: Programming Language :: Python :: 3.10
Classifier: Programming Language :: Python :: 3.11
Classifier: Programming Language :: Python :: 3.12
Provides-Extra: images
Requires-Dist: gigachain-core (>=0.2.38post2,<0.4)
Requires-Dist: google-generativeai (>=0.7.0,<0.8.0)
Requires-Dist: pillow (>=10.1.0,<11.0.0) ; extra == "images"
Requires-Dist: pydantic (>=2,<3)
Project-URL: Repository, https://github.com/langchain-ai/langchain-google
Project-URL: Source Code, https://github.com/langchain-ai/langchain-google/tree/main/libs/genai
